MANIFEST.in
README.txt
sc.releaser.cfg
setup.cfg
setup.py
beyondskins/__init__.py
beyondskins.ploneday.site.egg-info/PKG-INFO
beyondskins.ploneday.site.egg-info/SOURCES.txt
beyondskins.ploneday.site.egg-info/dependency_links.txt
beyondskins.ploneday.site.egg-info/entry_points.txt
beyondskins.ploneday.site.egg-info/namespace_packages.txt
beyondskins.ploneday.site.egg-info/not-zip-safe
beyondskins.ploneday.site.egg-info/requires.txt
beyondskins.ploneday.site.egg-info/top_level.txt
beyondskins/ploneday/__init__.py
beyondskins/ploneday/site/README.txt
beyondskins/ploneday/site/__init__.py
beyondskins/ploneday/site/configure.zcml
beyondskins/ploneday/site/profiles.zcml
beyondskins/ploneday/site/setuphandlers.py
beyondskins/ploneday/site/skins.zcml
beyondskins/ploneday/site/tests.py
beyondskins/ploneday/site/version.txt
beyondskins/ploneday/site/browser/__init__.py
beyondskins/ploneday/site/browser/configure.zcml
beyondskins/ploneday/site/browser/interfaces.py
beyondskins/ploneday/site/browser/viewlets.py
beyondskins/ploneday/site/browser/images/README.txt
beyondskins/ploneday/site/browser/stylesheets/README.txt
beyondskins/ploneday/site/browser/templates/footer.pt
beyondskins/ploneday/site/browser/templates/viewlet.pt
beyondskins/ploneday/site/doc/__init__.py
beyondskins/ploneday/site/doc/screenshot.png
beyondskins/ploneday/site/doc/wpd-portal-top.xcf
beyondskins/ploneday/site/locales/beyondskins.ploneday.site.pot
beyondskins/ploneday/site/locales/pt_BR/LC_MESSAGES/beyondskins.ploneday.site.mo
beyondskins/ploneday/site/locales/pt_BR/LC_MESSAGES/beyondskins.ploneday.site.po
beyondskins/ploneday/site/profiles/default/actions.xml
beyondskins/ploneday/site/profiles/default/beyondskins.site_various.txt
beyondskins/ploneday/site/profiles/default/cssregistry.xml
beyondskins/ploneday/site/profiles/default/import_steps.xml
beyondskins/ploneday/site/profiles/default/jsregistry.xml
beyondskins/ploneday/site/profiles/default/metadata.xml
beyondskins/ploneday/site/profiles/default/skins.xml
beyondskins/ploneday/site/profiles/default/viewlets.xml
beyondskins/ploneday/site/skins/beyondskins_ploneday_site_images/CONTENT.txt
beyondskins/ploneday/site/skins/beyondskins_ploneday_site_images/background.gif
beyondskins/ploneday/site/skins/beyondskins_ploneday_site_images/background.gif.metadata
beyondskins/ploneday/site/skins/beyondskins_ploneday_site_images/banner.jpg
