Metadata-Version: 1.0
Name: beyondskins.ploneday.site
Version: 1.0.2
Summary: Installable Plone 3 theme for World Plone Day
Home-page: http://www.simplesconsultoria.com.br/
Author: Simples Consultoria
Author-email: products@simplesconsultoria.com.br
License: GPL
Keywords: web zope plone theme skin simples_consultoria plone3
Platform: UNKNOWN
Classifier: Framework :: Plone
Classifier: Framework :: Zope2
Classifier: Framework :: Zope3
Classifier: Programming Language :: Python
Classifier: Topic :: Software Development :: Libraries :: Python Modules
